asyncdex/__init__.py
asyncdex/client.py
asyncdex/constants.py
asyncdex/enum.py
asyncdex/exceptions.py
asyncdex/list_orders.py
asyncdex/ratelimit.py
asyncdex/utils.py
asyncdex/version.py
asyncdex/models/__init__.py
asyncdex/models/abc.py
asyncdex/models/aggregate.py
asyncdex/models/author.py
asyncdex/models/chapter.py
asyncdex/models/chapter_list.py
asyncdex/models/client_user.py
asyncdex/models/cover_art.py
asyncdex/models/cover_list.py
asyncdex/models/custom_list.py
asyncdex/models/group.py
asyncdex/models/manga.py
asyncdex/models/manga_list.py
asyncdex/models/mixins.py
asyncdex/models/pager.py
asyncdex/models/tag.py
asyncdex/models/title.py
asyncdex/models/user.py
AsyncDex-1.1.dist-info/LICENSE
AsyncDex-1.1.dist-info/METADATA
AsyncDex-1.1.dist-info/WHEEL
AsyncDex-1.1.dist-info/top_level.txt
AsyncDex-1.1.dist-info/RECORD
